speddbase-0.1.0.dist-info/METADATA
speddbase-0.1.0.dist-info/WHEEL
psbase/__init__.py
psbase/psbase.cpython-39-aarch64-linux-gnu.so
speddbase-0.1.0.dist-info/RECORD
